pcli/__init__.py
pcli/api/__init__.py
pcli/api/accelerator_type.py
pcli/api/billing.py
pcli/api/inference.py
pcli/api/instance_type.py
pcli/api/job.py
pcli/api/model_template.py
pcli/api/organization.py
pcli/cli.py
pcli/colors.py
pcli/commands/__init__.py
pcli/commands/accelerator_type.py
pcli/commands/billing.py
pcli/commands/config.py
pcli/commands/currency.py
pcli/commands/inference.py
pcli/commands/instance_type.py
pcli/commands/job.py
pcli/commands/model_template.py
pcli/commands/registry.py
pcli/responses.py
pcli/settings.py
pcli/util/__init__.py
pcli/util/currencies.py
pcli/util/db.py
pcli/util/formatter.py
pcli/util/organization.py
pcli/util/rich_utils.py
pcli/util/setup.py
pcli/util/string_similarity.py
perian_cli-0.3.6.dist-info/METADATA
perian_cli-0.3.6.dist-info/WHEEL
perian_cli-0.3.6.dist-info/entry_points.txt
perian_cli-0.3.6.dist-info/RECORD
