Metadata-Version: 2.1
Name: perian-cli
Version: 0.3.6
Summary: PERIAN Sky Platform CLI
Home-page: https://perian.io
Keywords: perian,sky,sky-computing,sky-platform,cli
Author: Perian
Author-email: info@perian.io
Requires-Python: >=3.10,<4.0
Classifier: Intended Audience :: Developers
Classifier: Intended Audience :: Science/Research
Classifier: Intended Audience :: System Administrators
Classifier: Programming Language :: Python :: 3
Classifier: Programming Language :: Python :: 3.10
Classifier: Programming Language :: Python :: 3.11
Classifier: Programming Language :: Python :: 3.12
Classifier: Topic :: Scientific/Engineering
Classifier: Topic :: Scientific/Engineering :: Artificial Intelligence
Classifier: Topic :: Software Development
Classifier: Topic :: System :: Distributed Computing
Classifier: Topic :: System :: Systems Administration
Requires-Dist: click (==8.1.7)
Requires-Dist: perian (==0.3.6)
Requires-Dist: pydantic (==2.10.5)
Requires-Dist: pydantic-settings (==2.2.1)
Requires-Dist: python-Levenshtein (==0.26.1)
Requires-Dist: requests (==2.31.0)
Requires-Dist: rich (==13.7.1)
Requires-Dist: toml (==0.10.2)
Requires-Dist: typer (==0.12.3)
Requires-Dist: validators (==0.28.1)
Project-URL: Documentation, https://perian.io
